LICENSE
MANIFEST.in
README.rst
setup.py
django_cofingo/__init__.py
django_cofingo/extensions.py
django_cofingo/filters.py
django_cofingo/library.py
django_cofingo/models.py
django_cofingo/utils.py
django_cofingo.egg-info/PKG-INFO
django_cofingo.egg-info/SOURCES.txt
django_cofingo.egg-info/dependency_links.txt
django_cofingo.egg-info/not-zip-safe
django_cofingo.egg-info/requires.txt
django_cofingo.egg-info/top_level.txt
django_cofingo/management/__init__.py
django_cofingo/management/commands/__init__.py
django_cofingo/management/commands/makemessages.py
django_cofingo/tests/__init__.py
django_cofingo/tests/test_environment.py
django_cofingo/tests/test_extensions.py
django_cofingo/tests/test_filters.py
django_cofingo/tests/test_fullstack.py
django_cofingo/tests/test_library.py
django_cofingo/tests/apps/__init__.py
django_cofingo/tests/apps/urls.py
django_cofingo/tests/apps/fullstack_app/__init__.py
django_cofingo/tests/apps/fullstack_app/helpers.py
django_cofingo/tests/apps/fullstack_app/urls.py
django_cofingo/tests/apps/fullstack_app/views.py
django_cofingo/tests/apps/fullstack_app/templates/fullstack_app/index.html
django_cofingo/tests/apps/urls_app/__init__.py
django_cofingo/tests/apps/urls_app/urls.py
django_cofingo/tests/apps/urls_app/views.py