Metadata-Version: 1.0
Name: django-cofingo
Version: 0.2.2
Summary: Jinja2 template renderer for Django
Home-page: http://github.com/mvantellingen/django-cofingo
Author: Michael van Tellingen
Author-email: michaelvantellingen@gmail.com
License: BSD
Platform: UNKNOWN
